odoo/addons/l10n_es_facturae_sale_stock/README.rst
odoo/addons/l10n_es_facturae_sale_stock/__init__.py
odoo/addons/l10n_es_facturae_sale_stock/__manifest__.py
odoo/addons/l10n_es_facturae_sale_stock/i18n/l10n_es_facturae_sale_stock.pot
odoo/addons/l10n_es_facturae_sale_stock/models/__init__.py
odoo/addons/l10n_es_facturae_sale_stock/models/account_move_line.py
odoo/addons/l10n_es_facturae_sale_stock/readme/CONTRIBUTORS.rst
odoo/addons/l10n_es_facturae_sale_stock/readme/DESCRIPTION.rst
odoo/addons/l10n_es_facturae_sale_stock/readme/INSTALL.rst
odoo/addons/l10n_es_facturae_sale_stock/static/description/icon.png
odoo/addons/l10n_es_facturae_sale_stock/static/description/index.html
odoo/addons/l10n_es_facturae_sale_stock/views/report_facturae.xml
odoo14_addon_l10n_es_facturae_sale_stock-14.0.1.0.1.dev3.dist-info/METADATA
odoo14_addon_l10n_es_facturae_sale_stock-14.0.1.0.1.dev3.dist-info/WHEEL
odoo14_addon_l10n_es_facturae_sale_stock-14.0.1.0.1.dev3.dist-info/top_level.txt
odoo14_addon_l10n_es_facturae_sale_stock-14.0.1.0.1.dev3.dist-info/RECORD
